LICENSE.md
pydantic2_argparse/__init__.py
pydantic2_argparse/__metadata__.py
pydantic2_argparse/argparse/__init__.py
pydantic2_argparse/argparse/actions.py
pydantic2_argparse/argparse/parser.py
pydantic2_argparse/argparse/patches.py
pydantic2_argparse/parsers/__init__.py
pydantic2_argparse/parsers/boolean.py
pydantic2_argparse/parsers/command.py
pydantic2_argparse/parsers/container.py
pydantic2_argparse/parsers/enum.py
pydantic2_argparse/parsers/literal.py
pydantic2_argparse/parsers/mapping.py
pydantic2_argparse/parsers/standard.py
pydantic2_argparse/py.typed
pydantic2_argparse/utils/__init__.py
pydantic2_argparse/utils/arguments.py
pydantic2_argparse/utils/errors.py
pydantic2_argparse/utils/namespaces.py
pydantic2_argparse/utils/pydantic.py
pydantic2_argparse/utils/types.py
pydantic2_argparse-0.9.2.dist-info/LICENSE.md
pydantic2_argparse-0.9.2.dist-info/METADATA
pydantic2_argparse-0.9.2.dist-info/WHEEL
pydantic2_argparse-0.9.2.dist-info/RECORD
