Metadata-Version: 2.1
Name: pydantic2-argparse
Version: 0.9.2
Summary: Typed Argument Parsing with Pydantic
Home-page: https://github.com/anastasds/pydantic2-argparse
License: MIT
Keywords: python,pydantic,argparse,typed,validation
Author: Hayden Richards
Author-email: SupImDos@gmail.com
Requires-Python: >=3.8,<4.0
Classifier: License :: OSI Approved :: MIT License
Classifier: Programming Language :: Python :: 3
Classifier: Programming Language :: Python :: 3.8
Classifier: Programming Language :: Python :: 3.9
Classifier: Programming Language :: Python :: 3.10
Classifier: Programming Language :: Python :: 3.11
Classifier: Programming Language :: Python :: 3.12
Requires-Dist: importlib_metadata (>=4) ; python_version < "3.8"
Requires-Dist: pydantic (==2.5.3)
Requires-Dist: pydantic-settings (>=2.1.0,<3.0.0)
Requires-Dist: typing_extensions (>=4) ; python_version < "3.8"
Project-URL: Repository, https://github.com/anastasds/pydantic2-argparse
